{
  "api": {
    "allowCors": "FUSESWAP_API_ALLOW_CORS",
    "secret": "FUSESWAP_API_SECRET",
    "tokenExpiresIn": "FUSESWAP_TOKEN_EXPIRES_IN",
    "port": "FUSESWAP_PORT",
    "timeout": "FUSESWAP_API_TIMEOUT"
  },
  "aws": {
    "secrets": {
      "secretId": "FUSESWAP_AWS_SECRET_ID",
       "manager": {
        "region": "FUSESWAP_AWS_SECRET_MANAGER_REGION"
      }
    }
  },
  "mongo": {
    "uri": "FUSESWAP_MONGO_URI",
    "debug": "FUSESWAP_MONGO_DEBUG"
  },
  "secrets": {
    "accounts": {
      "seed": "FUSESWAP_SECRETS_ACCOUNTS_SEED"
    }
  },
  "rpcUrl": "FUSESWAP_RPC_URL"
}
